openfeature/contrib/provider/unleash/__init__.py
openfeature/contrib/provider/unleash/events.py
openfeature/contrib/provider/unleash/flag_evaluation.py
openfeature_provider_unleash-0.1.1.dist-info/WHEEL
openfeature_provider_unleash-0.1.1.dist-info/entry_points.txt
openfeature_provider_unleash-0.1.1.dist-info/METADATA
openfeature_provider_unleash-0.1.1.dist-info/RECORD
