Metadata-Version: 2.3
Name: openfeature-provider-unleash
Version: 0.1.1
Summary: OpenFeature provider for Unleash
Keywords: 
Author: OpenFeature
Author-email: OpenFeature <openfeature-core@groups.io>
License:                                  Apache License
Classifier: License :: OSI Approved :: Apache Software License
Classifier: Programming Language :: Python
Classifier: Programming Language :: Python :: 3
Requires-Dist: openfeature-sdk>=0.8.2
Requires-Dist: unleashclient>=6.3.0
Requires-Python: >=3.9
Project-URL: Homepage, https://github.com/open-feature/python-sdk-contrib
